authz_analyzer/__init__.py
authz_analyzer/cli.py
authz_analyzer/datastores/__init__.py
authz_analyzer/datastores/aws/__init__.py
authz_analyzer/datastores/aws/analyzer/__init__.py
authz_analyzer/datastores/aws/analyzer/analyzer.py
authz_analyzer/datastores/aws/analyzer/exporter.py
authz_analyzer/datastores/aws/analyzer/redshift/__init__.py
authz_analyzer/datastores/aws/analyzer/redshift/analyzer.py
authz_analyzer/datastores/aws/analyzer/redshift/commands/all_databases.sql
authz_analyzer/datastores/aws/analyzer/redshift/commands/all_tables.sql
authz_analyzer/datastores/aws/analyzer/redshift/commands/datashare_consumers.sql
authz_analyzer/datastores/aws/analyzer/redshift/commands/datashare_desc.sql
authz_analyzer/datastores/aws/analyzer/redshift/commands/datashares.sql
authz_analyzer/datastores/aws/analyzer/redshift/commands/identities.sql
authz_analyzer/datastores/aws/analyzer/redshift/commands/identities_privileges.sql
authz_analyzer/datastores/aws/analyzer/redshift/exporter.py
authz_analyzer/datastores/aws/analyzer/redshift/model.py
authz_analyzer/datastores/aws/analyzer/redshift/service.py
authz_analyzer/datastores/aws/aws_ptrp_package/aws_ptrp/__init__.py
authz_analyzer/datastores/aws/aws_ptrp_package/aws_ptrp/actions/__init__.py
authz_analyzer/datastores/aws/aws_ptrp_package/aws_ptrp/actions/actions_resolver.py
authz_analyzer/datastores/aws/aws_ptrp_package/aws_ptrp/actions/aws_actions.py
authz_analyzer/datastores/aws/aws_ptrp_package/aws_ptrp/iam/__init__.py
authz_analyzer/datastores/aws/aws_ptrp_package/aws_ptrp/iam/iam_entities.py
authz_analyzer/datastores/aws/aws_ptrp_package/aws_ptrp/iam/iam_groups.py
authz_analyzer/datastores/aws/aws_ptrp_package/aws_ptrp/iam/iam_policies.py
authz_analyzer/datastores/aws/aws_ptrp_package/aws_ptrp/iam/iam_roles.py
authz_analyzer/datastores/aws/aws_ptrp_package/aws_ptrp/iam/iam_users.py
authz_analyzer/datastores/aws/aws_ptrp_package/aws_ptrp/iam/policy/__init__.py
authz_analyzer-0.1.12.dist-info/LICENSE
authz_analyzer-0.1.12.dist-info/METADATA
authz_analyzer-0.1.12.dist-info/WHEEL
authz_analyzer-0.1.12.dist-info/entry_points.txt
authz_analyzer-0.1.12.dist-info/RECORD
