Metadata-Version: 2.1
Name: authz-analyzer
Version: 0.1.12
Summary: Analyze authorization.
Home-page: https://github.com/satoricyber/authz-analyzer
Author: SatoriCyber
Requires-Python: >=3.8.1,<3.11
Classifier: Development Status :: 4 - Beta
Classifier: Intended Audience :: Developers
Classifier: Natural Language :: English
Classifier: Programming Language :: Python :: 3
Classifier: Programming Language :: Python :: 3.9
Classifier: Programming Language :: Python :: 3.10
Classifier: Programming Language :: Python :: 3
Classifier: Programming Language :: Python :: 3.10
Classifier: Programming Language :: Python :: 3.8
Classifier: Programming Language :: Python :: 3.9
Provides-Extra: release
Provides-Extra: test
Requires-Dist: black (>=22.12.0,<23.0.0) ; extra == "test"
Requires-Dist: boto3 (>=1.26.27,<2.0.0)
Requires-Dist: bump2version (>=1.0.1,<2.0.0) ; extra == "test"
Requires-Dist: click (==8.1.3)
Requires-Dist: databricks-cli (>=0.17.4,<0.18.0)
Requires-Dist: google-api-python-client (>=2.66.0,<2.67.0)
Requires-Dist: google-api-python-client-stubs (>=1.13.0,<2.0.0) ; extra == "test"
Requires-Dist: google-cloud-bigquery (>=2.1.0,<3.0)
Requires-Dist: google-cloud-iam (>=2.10.0,<3.0.0)
Requires-Dist: google-cloud-resource-manager (>=1.6.3,<2.0)
Requires-Dist: isort (>=5.11.3,<6.0.0) ; extra == "test"
Requires-Dist: markdown-it-py (>=2.2.0,<3.0.0)
Requires-Dist: mkdocs (>=1.4.2,<2.0.0) ; extra == "release"
Requires-Dist: mkdocs-include-markdown-plugin (>=4.0.3,<5.0.0) ; extra == "release"
Requires-Dist: mkdocs-material (>=9.0.12,<10.0.0) ; extra == "release"
Requires-Dist: mypy (>=0.991,<0.992) ; extra == "test"
Requires-Dist: networkx (>=2.8.8,<3.0.0)
Requires-Dist: pip (>=22.3.1,<23.0.0)
Requires-Dist: pre-commit (>=2.20.0,<3.0.0)
Requires-Dist: psycopg2 (>=2.9.5,<3.0.0)
Requires-Dist: psycopg2-binary (>=2.9.5,<3.0.0)
Requires-Dist: pydantic (>=1.10.2,<2.0.0)
Requires-Dist: pylint (>=2.16.2,<3.0.0) ; extra == "test"
Requires-Dist: pymongo (>=4.3.3,<5.0.0)
Requires-Dist: pyright (>=1.1.293,<2.0.0) ; extra == "test"
Requires-Dist: pyserde (>=0.9.6,<0.10.0)
Requires-Dist: pytest (>=7.2.0,<8.0.0) ; extra == "test"
Requires-Dist: pytest-cov (>=4.0.0,<5.0.0) ; extra == "test"
Requires-Dist: redshift-connector (>=2.0.909,<3.0.0)
Requires-Dist: requests (>=2.28.1,<3.0.0)
Requires-Dist: snowflake-connector-python (==3.0.0)
Requires-Dist: tox (>=4.0.14,<5.0.0)
Requires-Dist: twine (>=4.0.2,<5.0.0) ; extra == "test" or extra == "release"
Requires-Dist: types-psycopg2 (>=2.9.21.2,<3.0.0.0) ; extra == "test"
Requires-Dist: types-requests (>=2.28.11.7,<3.0.0.0) ; extra == "test"
Requires-Dist: virtualenv (>=20.17.1,<21.0.0)
